myprotosql/__init__.py
myprotosql/install_myproto.sql
myprotosql/myprotosql.py
myprotosql/uninstall_myproto.sql
myprotosql-0.0.8.dist-info/COPYING
myprotosql-0.0.8.dist-info/COPYING.LESSER
myprotosql-0.0.8.dist-info/METADATA
myprotosql-0.0.8.dist-info/WHEEL
myprotosql-0.0.8.dist-info/entry_points.txt
myprotosql-0.0.8.dist-info/top_level.txt
myprotosql-0.0.8.dist-info/RECORD
