Metadata-Version: 2.1
Name: myprotosql
Version: 0.0.8
Summary: Read protobuf binary data using vanilla mysql stored functions
Home-page: https://github.com/janickr/myprotosql
Author: Janick Reynders
License: GNU Lesser General Public License v3 or later (LGPLv3+)
Keywords: protoc,protobuf,mysql
Classifier: Programming Language :: Python :: 3
Classifier: Programming Language :: Python :: 3.9
Classifier: Programming Language :: Python :: 3.10
Classifier: License :: OSI Approved :: GNU Lesser General Public License v3 or later (LGPLv3+)
Classifier: Operating System :: OS Independent
Classifier: Topic :: Software Development :: Libraries :: Python Modules
Requires-Python: >=3.9
License-File: COPYING
License-File: COPYING.LESSER
Requires-Dist: protobuf>=5.27.2
